MANIFEST.in
setup.cfg
setup.py
require/common.txt
require/test.txt
splashio/__init__.py
splashio/config.py
splashio/splash.py
splashio.egg-info/PKG-INFO
splashio.egg-info/SOURCES.txt
splashio.egg-info/dependency_links.txt
splashio.egg-info/requires.txt
splashio.egg-info/top_level.txt