Metadata-Version: 1.1
Name: splashio
Version: 0.0.3
Summary: The splash SDK server.
Home-page: https://github.com/Splash-io
Author: Dawson Reid
Author-email: dreid93@gmail.com
License: UNKNOWN
Download-URL: https://github.com/Splash-io/splash-python/archive/0.0.2.tar.gz
Keywords: splash,sdk,event
Platform: UNKNOWN
